MANIFEST.in
requirements.txt
setup.py
examples/defaults.cfg
examples/gnups-coincident.cfg
examples/gnups-distinct.cfg
worch/__init__.py
worch/upstools/__init__.py
worch_ups.egg-info/PKG-INFO
worch_ups.egg-info/SOURCES.txt
worch_ups.egg-info/dependency_links.txt
worch_ups.egg-info/namespace_packages.txt
worch_ups.egg-info/requires.txt
worch_ups.egg-info/top_level.txt