Metadata-Version: 1.0
Name: worch-ups
Version: 0.5.0
Summary: Worch/waf tools and features for working with UPS.
Home-page: http://github.com/brettviren/worch-ups
Author: Brett Viren
Author-email: brett.viren@gmail.com
License: GPLv2
Platform: UNKNOWN
